[1,["f12a23c4-b924-4322-a260-3d982428f1e8@f9941","45828f25-b50d-4c52-a591-e19491a62b8c@f9941","7d8f9b89-4fd1-4c9f-a3ab-38ec7cded7ca@f9941","45828f25-b50d-4c52-a591-e19491a62b8c@6c48a"],["node","_spriteFrame","_normalSprite","_textureSource","root","toggleVibrate","toggleSfx","toggleMusic","data"],[["cc.Node",["_name","_layer","_components","_prefab","_children","_parent","_lpos"],1,9,4,2,1,5],["cc.Sprite",["_sizeMode","node","__prefab","_spriteFrame","_color"],2,1,4,6,5],["cc.Node",["_name","_layer","_parent","_components","_prefab","_lpos","_children"],1,1,12,4,5,2],["cc.Label",["_string","_actualFontSize","_isBold","node","__prefab","_color"],0,1,4,5],"cc.SpriteFrame",["cc.Prefab",["_name"],2],["cc.UITransform",["node","__prefab","_contentSize"],3,1,4,5],["cc.CompPrefabInfo",["fileId"],2],["cc.Widget",["_alignFlags","_originalWidth","_originalHeight","node","__prefab"],0,1,4],["83a3ea6LEpMNpOb3XWuaUZv",["node","__prefab","toggleMusic","toggleSfx","toggleVibrate"],3,1,4,1,1,1],["cc.PrefabInfo",["fileId","instance","targetOverrides","nestedPrefabInstanceRoots","root","asset"],-1,1,1],["8baf0yRYgpD9ICy72Y/wYVK",["duration","easename","node","__prefab"],1,1,4],["cc.Button",["_transition","_zoomScale","node","__prefab"],1,1,4],["6c292Xw629KQL+aYSS7yZ+/",["node","__prefab"],3,1,4],["fe582yImf9IKaHrahCHHNuH",["audioName","node","__prefab"],2,1,4],["cc.BlockInputEvents",["node","__prefab"],3,1,4],["cc.Toggle",["node","__prefab","checkEvents","_checkMark"],3,1,4,9,1],["cc.ClickEvent",["_componentId","handler","target"],1,1]],[[7,0,2],[6,0,1,2,1],[10,0,1,2,3,4,5,5],[0,0,1,5,2,3,3],[0,0,1,5,4,2,3,6,3],[1,0,1,2,2],[1,0,1,2,4,3,2],[14,0,1,2,2],[2,0,1,2,6,3,4,5,3],[1,1,2,1],[3,0,1,3,4,5,3],[16,0,1,2,3,1],[17,0,1,2,3],[2,0,1,2,3,4,3],[8,0,1,2,3,4,4],[5,0,2],[0,0,1,4,2,3,3],[0,0,1,5,4,2,3,3],[2,0,1,2,3,4,5,3],[9,0,1,2,3,4,1],[1,0,1,2,3,2],[11,0,1,2,3,3],[12,0,1,2,3,3],[13,0,1,1],[15,0,1,1],[3,0,1,2,3,4,5,4]],[[[{"name":"default_radio_button_on","rect":{"x":1,"y":1,"width":30,"height":30},"offset":{"x":0,"y":0},"originalSize":{"width":32,"height":32},"rotated":false,"capInsets":[0,0,0,0],"vertices":{"rawPosition":[-15,-15,0,15,-15,0,-15,15,0,15,15,0],"indexes":[0,1,2,2,1,3],"uv":[1,31,31,31,1,1,31,1],"nuv":[0.03125,0.03125,0.96875,0.03125,0.03125,0.96875,0.96875,0.96875],"minPos":{"x":-15,"y":-15,"z":0},"maxPos":{"x":15,"y":15,"z":0}},"packable":true,"pixelsToUnit":100,"pivot":{"x":0.5,"y":0.5},"meshType":0}],[4],0,[0],[3],[3]],[[[15,"SettingView"],[16,"SettingView",33554432,[-8,-9],[[1,-2,[0,"f12zKRoK5JEY+byS5iWthP"],[5,1080,1920]],[14,45,100,100,-3,[0,"32ELiAabFOTrctANdw2/6Y"]],[19,-7,[0,"cds3xHkf5OSaLq9QyvB1E5"],-6,-5,-4]],[2,"87qgYJeXdPvputF/yz22uj",null,null,null,-1,0]],[17,"dialog",33554432,1,[-13,-14,-15,-16,-17,-18,-19],[[1,-10,[0,"7brW4m2hFB3Ihh5kMZAKzM"],[5,785,541]],[20,0,-11,[0,"d69OCCaC5GN66G8NIkNcX3"],4],[21,0.3,"backOut",-12,[0,"2eIcVP/PFEkawB0uWll06Z"]]],[2,"ab+LCZ0+VGj5Lt5YyqWpnD",null,null,null,1,0]],[4,"shengji_2",33554432,2,[-25],[[1,-20,[0,"49brEhaINPY6s3I/r0OTD9"],[5,73,73]],[5,0,-21,[0,"3dRlwAXBtPTJQw/dvSs7ko"]],[22,3,0.9,-22,[0,"904hZTZNhCioXGTk7n59QA"]],[23,-23,[0,"b6iNk882BN3KXS1IrVhN/m"]],[7,"ui_back",-24,[0,"48o/6AUfJGAJvPkRpamWyp"]]],[2,"52+iIcNcxNSqxkO0jrZbO0",null,null,null,1,0],[1,352.581,231.508,0]],[8,"shezhi_1",33554432,2,[-30],[[[1,-26,[0,"a60p+foS9Efoi+FYLGyL01"],[5,35,35]],[6,0,-27,[0,"3eb4WVdV9GyaErsbcNCWt5"],[4,4282795590],1],-28,[7,"ui_click",-29,[0,"7f9Pau4SZC0r71hcYKYCvD"]]],4,4,1,4],[2,"2ehTX6kgVJFKlLGDkISxkW",null,null,null,1,0],[1,139.848,113.211,0]],[8,"shezhi_2",33554432,2,[-35],[[[1,-31,[0,"61WhnEIixFP73QYAyL+IPD"],[5,35,35]],[6,0,-32,[0,"ea0klA8vhHp45Zj33L7iWO"],[4,4282795590],2],-33,[7,"ui_click",-34,[0,"7ckfshUlVK1pboKnSkA7R8"]]],4,4,1,4],[2,"595z5ulPVIrqf1clnoU4be",null,null,null,1,0],[1,139.848,-19.978,0]],[8,"shezhi_6",33554432,2,[-40],[[[1,-36,[0,"a6HBkycGlGwJWQ1TZIj0Ah"],[5,35,35]],[6,0,-37,[0,"a3OzEv9qtFiqvzjxajUVaw"],[4,4282795590],3],-38,[7,"ui_click",-39,[0,"e7JoGxTA9Bgr3c2jLICCst"]]],4,4,1,4],[2,"d68rtoPEVNS7IjwAibH0lL",null,null,null,1,0],[1,139.848,-144.842,0]],[3,"bg",33554432,1,[[1,-41,[0,"f96VeMUrRFuoa2Mq3F/xds"],[5,1080,1920]],[6,0,-42,[0,"49NJz3Ap9OC40lrh3v30vx"],[4,3019898880],0],[14,45,100,100,-43,[0,"bftYkyfrBGJ748+pnLYaJq"]],[24,-44,[0,"bctzbp8gpHxIpjiYXIWema"]]],[2,"20xuVfoItIHrdTCjXZ71n5",null,null,null,1,0]],[4,"shezhi_3",33554432,2,[-47],[[1,-45,[0,"06xOKxptVNO5IKbYy1x8Hj"],[5,264,131]],[5,0,-46,[0,"b4xXrjy5ZE/4EHpFIvrnW3"]]],[2,"c0nt90LzVFtYsgqDqeraMY",null,null,null,1,0],[1,-139.038,114.875,0]],[4,"shezhi_4",33554432,2,[-50],[[1,-48,[0,"00BwQSKtVOJKtdcik/NE8i"],[5,264,131]],[5,0,-49,[0,"ebbfUw+s9E8arr3Qy4rRqI"]]],[2,"efzwrpwHhH3ZpSTQu1eJ1V",null,null,null,1,0],[1,-139.038,-19.978,0]],[4,"shezhi_5",33554432,2,[-53],[[1,-51,[0,"71MwfzbghI0bqqDG/gMOoq"],[5,264,131]],[5,0,-52,[0,"488Rz30ftGV4A4lNV8fG5P"]]],[2,"d1cyom/ixGN5Wd0+zppdOp",null,null,null,1,0],[1,-139.038,-144.842,0]],[3,"Label",33554432,8,[[1,-54,[0,"d3Y6KWxA1IJa/YNNglnpBA"],[5,80,50.4]],[10,"音乐",40,-55,[0,"222TFMbTdI5ruOLvM87DcN"],[4,4278190080]]],[2,"b3NyZkjLZHroThcVOqwcWm",null,null,null,1,0]],[3,"Label",33554432,9,[[1,-56,[0,"d7amt3notCUb4lkJqyNeTd"],[5,80,50.4]],[10,"音效",40,-57,[0,"efeCqi9LFGfJIjwYLHIdHP"],[4,4278190080]]],[2,"80K0Xf0UxGn62WsuTm9Cbi",null,null,null,1,0]],[3,"Label",33554432,10,[[1,-58,[0,"60AOA1tLBIapkOCxd9TQdb"],[5,80,50.4]],[10,"震动",40,-59,[0,"a8YpUAR7pKYJa2pRXTHrE6"],[4,4278190080]]],[2,"16u52q9J1NkqhNRszUtHk3",null,null,null,1,0]],[18,"shezhi_2",33554432,4,[[[1,-60,[0,"3fngiIY31B2b6r8chJo4il"],[5,30,30]],-61],4,1],[2,"0fvnli0vNMjZ/RYqkm8hqP",null,null,null,1,0],[1,0,0.478,0]],[13,"shezhi_2",33554432,5,[[[1,-62,[0,"4bsebocPtIhJmvk7woT0iG"],[5,30,30]],-63],4,1],[2,"18vyIp4WdHQKyqEIHK8LxV",null,null,null,1,0]],[13,"shezhi_2",33554432,6,[[[1,-64,[0,"6cCFE5MxVM7IbE1UmFAw55"],[5,30,30]],-65],4,1],[2,"b1IKsEM81HFpxTtAiB+ZGT",null,null,null,1,0]],[3,"Label",33554432,3,[[1,-66,[0,"f6b67iObpMgJOP9oycWOqk"],[5,26.6796875,50.4]],[25,"X",40,true,-67,[0,"5byYKHKzJKPrMK2OJWEdEd"],[4,4278190080]]],[2,"aeroLyr0FFR6ZCWYPTnqED",null,null,null,1,0]],[9,14,[0,"265B7xV8RPPppK2p/yNpzV"]],[11,4,[0,"c0eitE3uZH8YhRU2VLb7NK"],[[12,"83a3ea6LEpMNpOb3XWuaUZv","onToggleMusic",1]],18],[9,15,[0,"d1AKrgGV9CFIclFGlLfL+W"]],[11,5,[0,"eeE1dv+LJNOZU1v5WeMAx5"],[[12,"83a3ea6LEpMNpOb3XWuaUZv","onToggleSoundEffect",1]],20],[9,16,[0,"07MZqKpMZMgJ4LQHURrPQF"]],[11,6,[0,"fba4+4WmlNKY8KoIZ25Qcg"],[[12,"83a3ea6LEpMNpOb3XWuaUZv","onToggleSoundEffect",1]],22]],0,[0,4,1,0,0,1,0,0,1,0,5,23,0,6,21,0,7,19,0,0,1,0,-1,7,0,-2,2,0,0,2,0,0,2,0,0,2,0,-1,8,0,-2,9,0,-3,10,0,-4,4,0,-5,5,0,-6,6,0,-7,3,0,0,3,0,0,3,0,0,3,0,0,3,0,0,3,0,-1,17,0,0,4,0,0,4,0,-3,19,0,0,4,0,-1,14,0,0,5,0,0,5,0,-3,21,0,0,5,0,-1,15,0,0,6,0,0,6,0,-3,23,0,0,6,0,-1,16,0,0,7,0,0,7,0,0,7,0,0,7,0,0,8,0,0,8,0,-1,11,0,0,9,0,0,9,0,-1,12,0,0,10,0,0,10,0,-1,13,0,0,11,0,0,11,0,0,12,0,0,12,0,0,13,0,0,13,0,0,14,0,-2,18,0,0,15,0,-2,20,0,0,16,0,-2,22,0,0,17,0,0,17,0,8,1,67],[0,0,0,0,0,18,19,20,21,22,23],[1,1,1,1,1,1,2,1,2,1,2],[2,0,0,0,2,1,0,1,0,1,0]]]]
